pcomp/__init__.py
pcomp/functions.py
pcomp-1.3.2.dist-info/LICENSE.txt
pcomp-1.3.2.dist-info/METADATA
pcomp-1.3.2.dist-info/WHEEL
pcomp-1.3.2.dist-info/top_level.txt
pcomp-1.3.2.dist-info/RECORD
