Metadata-Version: 2.1
Name: pcomp
Version: 1.3.2
Summary: Possible permutations with repetition - Python Library
Home-page: https://github.com/AntonisPilo/pcomp
Author: Antonis Piloridis
Author-email: antonispiloridis@gmail.com
License: MIT
Keywords: permutations,permutations with repetition
Platform: UNKNOWN
Classifier: Development Status :: 5 - Production/Stable
Classifier: Intended Audience :: Developers
Classifier: Operating System :: Microsoft :: Windows :: Windows 11
Classifier: License :: OSI Approved :: MIT License
Classifier: Programming Language :: Python :: 3
Requires-Python: >=3.3
